smos/Grid_Point_Mask_USGS.nc
smos/__init__.py
smos/grid.py
smos/interface.py
smos/misc.py
smos/reshuffle.py
smos/smos_ic/__init__.py
smos/smos_ic/download.py
smos/smos_ic/interface_ic.py
smos/smos_ic/mask_and_flatten_gridfile.ipynb
smos/smos_ic/reshuffle_ic.py
smos/smos_l2/cli.py
smos/smos_l2/download.py
smos/smos_l2/reshuffle.py
smos/smos_l3/download.py
smos/smos_l3/mask_and_flatten_gridfile.ipynb
smos/smos_l4/__init__.py
smos/smos_l4/interface_l4.py
smos/smos_l4/reshuffle_l4.py
smos-0.4.dist-info/AUTHORS.rst
smos-0.4.dist-info/LICENSE.txt
smos-0.4.dist-info/METADATA
smos-0.4.dist-info/WHEEL
smos-0.4.dist-info/entry_points.txt
smos-0.4.dist-info/top_level.txt
smos-0.4.dist-info/RECORD
