Metadata-Version: 2.1
Name: smos
Version: 0.4
Summary: SMOS (Soil Moisture and Ocean Salinity) image data readers and TS converter
Home-page: https://github.com/TUW-GEO/smos
Author: TU Wien
Author-email: remote.sensing@geo.tuwien.ac.at
License: mit
Project-URL: Documentation, https://smos.readthedocs.io/en/latest/
Platform: any
Classifier: Development Status :: 4 - Beta
Classifier: Programming Language :: Python
License-File: LICENSE.txt
License-File: AUTHORS.rst
Requires-Dist: numpy
Requires-Dist: scipy
Requires-Dist: pandas
Requires-Dist: dask[distributed]
Requires-Dist: xarray
Requires-Dist: netCDF4
Requires-Dist: repurpose>=0.13.1
Requires-Dist: pyresample
Requires-Dist: pygeogrids>=0.3.2
Requires-Dist: pynetcf>=0.5.1
Requires-Dist: pygeobase
Requires-Dist: ease-grid
Requires-Dist: trollsift
Requires-Dist: h5py
Requires-Dist: more-itertools
Requires-Dist: cf-xarray
Requires-Dist: qa4sm-preprocessing>=0.5
Requires-Dist: importlib-metadata; python_version < "3.8"
Provides-Extra: testing
Requires-Dist: pytest-cov; extra == "testing"
Requires-Dist: pytest; extra == "testing"
